{
  "type": "minecraft:crafting_shapeless",
  "ingredients": [
    {
      "tag": "c:gems/alexandrite"
    },
    {
      "tag": "c:gems/alexandrite"
    },
    {
      "tag": "c:gems/alexandrite"
    },
    {
      "tag": "c:gems/alexandrite"
    },
    {
      "tag": "c:gems/alexandrite"
    },
    {
      "tag": "c:gems/alexandrite"
    },
    {
      "tag": "c:gems/alexandrite"
    },
    {
      "tag": "c:gems/alexandrite"
    },
    {
      "tag": "c:gems/alexandrite"
    }
  ],
  "result": {
    "id": "richstuff:alexandrite_block"
  }
}